{
  "realtime_start": "2025-09-13",
  "realtime_end": "2025-09-13",
  "seriess": [
    {
      "id": "TB6MS",
      "realtime_start": "2025-09-13",
      "realtime_end": "2025-09-13",
      "title": "6-Month Treasury Bill Secondary Market Rate, Discount Basis",
      "observation_start": "1958-12-01",
      "observation_end": "2025-08-01",
      "frequency": "Monthly",
      "frequency_short": "M",
      "units": "Percent",
      "units_short": "%",
      "seasonal_adjustment": "Not Seasonally Adjusted",
      "seasonal_adjustment_short": "NSA",
      "last_updated": "2025-09-02 15:16:53-05",
      "popularity": 28,
      "notes": "data source (https://www.federalreserve.gov/apps/ContactUs/feedback.aspx?refurl=/releases/h15/%). For questions on FRED functionality, please contact us here (https://fred.stlouisfed.org/contactus/).</p>"
    }
  ]
}