{
  "realtime_start": "2025-09-08",
  "realtime_end": "2025-09-08",
  "seriess": [
    {
      "id": "DEXUSUK",
      "realtime_start": "2025-09-08",
      "realtime_end": "2025-09-08",
      "title": "U.S. Dollars to U.K. Pound Sterling Spot Exchange Rate",
      "observation_start": "1971-01-04",
      "observation_end": "2025-09-05",
      "frequency": "Daily",
      "frequency_short": "D",
      "units": "U.S. Dollars to One U.K. Pound Sterling",
      "units_short": "U.S. $ to  1 U.K. Pound Sterling",
      "seasonal_adjustment": "Not Seasonally Adjusted",
      "seasonal_adjustment_short": "NSA",
      "last_updated": "2025-09-08 15:19:45-05",
      "popularity": 66,
      "notes": "Noon buying rates in New York City for cable transfers payable in foreign currencies."
    }
  ]
}