{
  "realtime_start": "2025-09-13",
  "realtime_end": "2025-09-13",
  "seriess": [
    {
      "id": "NOTEVALUE",
      "realtime_start": "2025-09-13",
      "realtime_end": "2025-09-13",
      "title": "Value of Notes Printed by Bureau of Engraving and Printing",
      "observation_start": "1993-01-01",
      "observation_end": "2024-01-01",
      "frequency": "Annual",
      "frequency_short": "A",
      "units": "Billions of Dollars",
      "units_short": "Bil. of $",
      "seasonal_adjustment": "Not Seasonally Adjusted",
      "seasonal_adjustment_short": "NSA",
      "last_updated": "2025-05-05 08:48:03-05",
      "popularity": 12
    }
  ]
}